mirrors_countme/__init__.py
mirrors_countme/constants.py
mirrors_countme/matchers.py
mirrors_countme/output_items.py
mirrors_countme/parse.py
mirrors_countme/progress.py
mirrors_countme/readers.py
mirrors_countme/regex.py
mirrors_countme/scripts/__init__.py
mirrors_countme/scripts/countme_delete_totals.py
mirrors_countme/scripts/countme_parse_access_log.py
mirrors_countme/scripts/countme_totals.py
mirrors_countme/scripts/countme_trim_raw.py
mirrors_countme/totals.py
mirrors_countme/util.py
mirrors_countme/version.py
mirrors_countme/writers.py
mirrors_countme-0.1.4.dist-info/LICENSE.md
mirrors_countme-0.1.4.dist-info/METADATA
mirrors_countme-0.1.4.dist-info/WHEEL
mirrors_countme-0.1.4.dist-info/entry_points.txt
mirrors_countme-0.1.4.dist-info/RECORD
