Metadata-Version: 2.1
Name: mirrors-countme
Version: 0.1.4
Summary: Parse access logs and count hosts for DNF mirrors
Home-page: http://github.com/fedora-infra/mirrors-countme
License: GPL-3.0-or-later
Author: Will Woods
Maintainer: Fedora Infrastructure
Maintainer-email: admin@fedoraproject.org
Requires-Python: >=3.11,<4.0
Classifier: License :: OSI Approved :: GNU General Public License v3 or later (GPLv3+)
Classifier: Programming Language :: Python :: 3
Classifier: Programming Language :: Python :: 3.11
Classifier: Programming Language :: Python :: 3.12
Project-URL: Repository, http://github.com/fedora-infra/mirrors-countme
